TIMESERIESTYPEDETERM/__init__.py
TIMESERIESTYPEDETERM/gui.py
TIMESERIESTYPEDETERM/smoothing.py
TIMESERIESTYPEDETERM/stationarity.py
TIMESERIESTYPEDETERM-0.1.dist-info/METADATA
TIMESERIESTYPEDETERM-0.1.dist-info/WHEEL
TIMESERIESTYPEDETERM-0.1.dist-info/top_level.txt
TIMESERIESTYPEDETERM-0.1.dist-info/RECORD
