Metadata-Version: 2.1
Name: TIMESERIESTYPEDETERM
Version: 0.1
Summary: timeseries analys
Author-email: mariapetrenko003@gmail.com
Requires-Dist: numpy
Requires-Dist: pandas
Requires-Dist: matplotlib
Requires-Dist: statsmodels
